yt6/__init__.py
yt6/__main__.py
yt6/yt6.py
yt6-1.5.5.dist-info/LICENSE
yt6-1.5.5.dist-info/METADATA
yt6-1.5.5.dist-info/WHEEL
yt6-1.5.5.dist-info/entry_points.txt
yt6-1.5.5.dist-info/top_level.txt
yt6-1.5.5.dist-info/RECORD
