Metadata-Version: 2.1
Name: yt6
Version: 1.5.5
Summary: Download audio and video from YouTube.
Home-page: https://github.com/Simatwa/yt6
Author: Smartwa Caleb
Author-email: smartwacaleb@gmail.com
Maintainer: Smartwa Caleb
License: MIT
Project-URL: Bug Report, https://github.com/Simatwa/yt6/issues/new
Keywords: yt5,yt6,youtubedl,youtube,downloader,video-downloader
Classifier: License :: OSI Approved :: MIT License
Classifier: Development Status :: 4 - Beta
Classifier: Intended Audience :: Developers
Classifier: Natural Language :: English
Classifier: License :: Free For Home Use
Classifier: Topic :: Home Automation
Classifier: Intended Audience :: Customer Service
Classifier: Programming Language :: Python
Classifier: Topic :: Software Development :: Libraries :: Python Modules
Classifier: Programming Language :: Python :: 3 :: Only
Classifier: Programming Language :: Python :: 3.8
Classifier: Programming Language :: Python :: 3.9
Classifier: Programming Language :: Python :: 3.10
Classifier: Programming Language :: Python :: 3.11
Requires-Python: >=3.8
License-File: LICENSE
Requires-Dist: colorama ==0.4.6
Requires-Dist: pytube >=15.0.0
Requires-Dist: tabulate ==0.9.0
